README.txt
setup.py
collective/__init__.py
collective.fastview.egg-info/PKG-INFO
collective.fastview.egg-info/SOURCES.txt
collective.fastview.egg-info/dependency_links.txt
collective.fastview.egg-info/entry_points.txt
collective.fastview.egg-info/namespace_packages.txt
collective.fastview.egg-info/not-zip-safe
collective.fastview.egg-info/paster_plugins.txt
collective.fastview.egg-info/requires.txt
collective.fastview.egg-info/top_level.txt
collective/fastview/__init__.py
collective/fastview/configure.zcml
collective/fastview/interfaces.py
collective/fastview/tests.py
collective/fastview/utilities.py
collective/fastview/views.py
docs/HISTORY.txt
docs/INSTALL.txt
docs/LICENSE.GPL
docs/LICENSE.txt