Metadata-Version: 1.0
Name: collective.fastview
Version: 0.2
Summary: View and viewlet helper modules for Plone theme and five.grok developers
Home-page: http://svn.plone.org/svn/collective/
Author: mFabrik Research Oy
Author-email: info@mfabrik.com
License: GPL
Keywords: five.grok viewlet view helper grok
Platform: UNKNOWN
Classifier: Framework :: Plone
Classifier: Programming Language :: Python
